setup.py
NBst1/__init__.py
NBst1/admin.py
NBst1/apps.py
NBst1/fields.py
NBst1/forms.py
NBst1/models.py
NBst1/states.py
NBst1/tests.py
NBst1/views.py
NBst1/migrations/__init__.py
nikhill_indian_states_25/__init__.py
nikhill_indian_states_25/asgi.py
nikhill_indian_states_25/settings.py
nikhill_indian_states_25/urls.py
nikhill_indian_states_25/wsgi.py
nikhill_indian_states_25.egg-info/PKG-INFO
nikhill_indian_states_25.egg-info/SOURCES.txt
nikhill_indian_states_25.egg-info/dependency_links.txt
nikhill_indian_states_25.egg-info/requires.txt
nikhill_indian_states_25.egg-info/top_level.txt